pyside6_uic_extended/__init__.py
pyside6_uic_extended/uic.py
unittests/__init__.py
unittests/test_uic.py
pyside6_uic_extended-0.0.1.dist-info/METADATA
pyside6_uic_extended-0.0.1.dist-info/WHEEL
pyside6_uic_extended-0.0.1.dist-info/entry_points.txt
pyside6_uic_extended-0.0.1.dist-info/top_level.txt
pyside6_uic_extended-0.0.1.dist-info/RECORD
